{
    "id": "Wandering Merchant",
    "nom": "Wandering Merchant",
    "rencontre": [
        {
            "type": "select",
            "speaker": "Wandering Merchant",
            "lines": [
                "Salutations, voyageur!",
                "Souhaitez-vous jeter un coup-d'oeil à mes marchandises?",
                "S'il vous plaît, cela fait si longtemps que je n'ai pas mangé..."
            ],
            "options": [
                {
                    "name": "Jeter un coup d'oeil",
                    "valeur": "1"
                },
                {
                    "name":"Discuter",
                    "valeur":"2"
                },
                {
                    "name": "Partir",
                    "valeur": "3"
                }
            ],
            "actions": {
                "1": [
                    {
                        "type": "boutique",
                        "shop_id":"merchant_shop",
                        "items": [
                            {
                                "id": "health_potion",
                                "prix": 10,
                                "stock":2
                            },
                            
                            {
                                "name": "fire resistance potion",
                                "prix":10,
                                "stock":1
                            },
                            {
                                "name": "strength potion",
                                "prix":20,
                                "stock":4
                            }
                        ]
                    }
                ],
                "3": [
                    {
                        "type": "dialogue",
                        "speaker": "Wandering Merchant",
                        "lines": [
                            "Bonne route"
                        ]
                    }
                ]
            }
        }
    ],
    "interaction": [
        {
            "type": "select",
            "speaker": "Wandering Merchant",
            "lines": [
                "Ah, bonjour",
                "C'est gentil de votre part de revenir me visiter. S'il vous plaît, venez m'acheter quelque chose, vous le voulez bien?"
            ],
            "options": [
                {
                    "name": "Jeter un coup d'oeil",
                    "valeur": "1"
                },
                {
                    "name":"Discuter",
                    "valeur":"2"
                },
                {
                    "name": "Partir",
                    "valeur": "3"
                }
            ],
            "actions": {
                "1": [
                    {
                        "type": "boutique",
                        "shop_id":"merchant_shop",
                        "items": [
                            {
                                "id": "health_potion",
                                "prix": 10,
                                "stock":2
                            },
                            
                            {
                                "name": "fire resistance potion",
                                "prix":10,
                                "stock":1
                            },
                            {
                                "name": "strength potion",
                                "prix":20,
                                "stock":4
                            }
                        ]
                    }
                ],
                "3": [
                    {
                        "type": "dialogue",
                        "speaker": "Wandering Merchant",
                        "lines": [
                            "Bonne route"
                        ]
                    }
                ]
            }
        }
    ]
}